README.rst
setup.py
src/pyramid_taobao/__init__.py
src/pyramid_taobao.egg-info/PKG-INFO
src/pyramid_taobao.egg-info/SOURCES.txt
src/pyramid_taobao.egg-info/dependency_links.txt
src/pyramid_taobao.egg-info/not-zip-safe
src/pyramid_taobao.egg-info/requires.txt
src/pyramid_taobao.egg-info/top_level.txt