Metadata-Version: 1.0
Name: pyramid-taobao
Version: 0.2
Summary: Pyramid configuration with OpenTaobao-API integration
Home-page: https://github.com/lxneng/pyramid_taobao
Author: Eric Lo
Author-email: lxneng@gmail.com
License: BSD
Platform: UNKNOWN
